{
  "schema_version": "report_display_terms_v1",
  "terms": {
    "ai_power_semiconductor_mosfet": "AI 電源與功率半導體 MOSFET",
    "ai_final_scoring_policy": "AI 最終評分規則",
    "analysis_model": "AI 模型",
    "analysis_model_choice": "模型選擇",
    "analysis_provider": "AI 服務商",
    "layer_market_validation": "盤面驗證層",
    "market_movers": "全市場強弱排行",
    "market_validated": "盤面驗證",
    "market_data_date": "市場資料日期",
    "report_generated_at": "報告產生時間",
    "source_mode": "資料來源模式",
    "hard_filter_policy": "硬篩選規則",
    "data_quality": "資料品質",
    "top_gainers": "漲幅排行",
    "top_losers": "跌幅排行",
    "top_volume_surge": "量增排行",
    "top_turnover": "成交值排行",
    "new_highs": "N 日新高",
    "new_lows": "N 日新低",
    "sector_mover_rankings": "族群強弱排行",
    "sector_rankings": "族群排行",
    "subsector_rankings": "子族群排行",
    "theme_rankings": "題材排行",
    "sector_strength": "族群強弱資料",
    "news_context": "新聞脈絡",
    "saved_news_context": "已保存新聞脈絡",
    "news_persistence_status": "新聞保存狀態",
    "feature_pack": "特徵資料包",
    "data_coverage": "資料覆蓋狀態",
    "data_gap_summary": "資料缺口摘要",
    "unified_evidence_pack": "共用證據包",
    "news_events": "新聞事件",
    "news_event_summary": "新聞事件摘要",
    "search_query_log": "搜尋紀錄",
    "report_quality": "報告品質",
    "report_quality_v1": "報告品質 v1",
    "data_completeness_matrix": "資料完整度矩陣",
    "data_coverage_score": "資料覆蓋分數",
    "source_coverage_summary": "來源覆蓋摘要",
    "source_quality": "來源品質",
    "source_quality_score": "來源品質分數",
    "source_quality_level": "來源品質等級",
    "qa_validation": "QA 檢查",
    "qa_warnings": "QA 提醒",
    "missing_data_policy": "缺資料解讀規則",
    "missing_fields": "缺漏欄位",
    "missing_data": "缺漏資料",
    "usable_count": "可用數量",
    "gap_count": "缺口數",
    "coverage_score": "覆蓋分數",
    "schema_version": "資料格式版本",
    "report_schema_version": "報告格式版本",
    "report_type": "報告類型",
    "target": "分析目標",
    "mode": "分析模式",
    "ai_used": "是否使用 AI",
    "fallback_reason": "降級原因",
    "created_at": "建立時間",
    "output_formats": "輸出格式",
    "segmented_ai_analysis": "分段 AI 分析",
    "segmented_ai_prompt_paths": "分段提示詞紀錄",
    "prompt_log_path": "提示詞紀錄路徑",
    "provider": "資料工具",
    "fetch_provider": "抓取工具",
    "provider_detail": "搜尋條件",
    "query": "搜尋詞",
    "task": "搜尋任務",
    "quality": "品質分數",
    "items": "項目",
    "summary": "摘要",
    "source_id": "來源編號",
    "title": "標題",
    "url": "連結",
    "source_url": "來源連結",
    "published_date": "發布日期",
    "snippet": "來源摘要",
    "event_count": "事件數",
    "news_signal_score": "新聞訊號分數",
    "news_heat_risk_score": "新聞熱度風險分數",
    "importance_score": "重要性分數",
    "representative_stocks": "代表股",
    "verified_representatives": "已驗證代表股",
    "inferred_representatives": "推論代表股",
    "representative_policy": "代表股判斷規則",
    "candidate_stocks": "候選觀察股",
    "counter_evidence": "反證",
    "command_role": "指令角色",
    "lookback_days": "觀察天數",
    "source": "來源",
    "available": "是否有資料",
    "count": "數量",
    "field": "資料欄位",
    "news_stats.news_count_24h": "近 24 小時新聞數",
    "active_breakout": "放量突破或轉強",
    "subsector_score": "子族群強度分數",
    "trend_pullback": "近期強勢後回檔整理",
    "cooling": "散熱",
    "verified": "已驗證",
    "inferred": "推論成立",
    "candidate": "候選觀察",
    "missing": "資料缺口",
    "evidence": "證據",
    "layer": "供應鏈層級",
    "active": "盤面活躍",
    "neutral": "中性",
    "high": "高",
    "medium": "中",
    "low": "低",
    "rejected": "排除",
    "L1_official": "官方來源",
    "L2_media": "媒體來源",
    "L3": "輔助來源",
    "L3_community": "社群與討論來源",
    "L4_social": "社群貼文來源",
    "Level 1": "官方來源",
    "Level 2": "媒體來源",
    "Level 3": "輔助來源",
    "Level 4": "社群貼文來源",
    "minimax_mcp_search": "MiniMax 網路搜尋",
    "gemini_search": "Gemini 網路搜尋",
    "tavily_extract": "Tavily 網頁擷取",
    "tavily_search": "Tavily 網路搜尋",
    "local_cache": "本地快取",
    "local_market_data": "本地市場資料",
    "unknown": "未標示",
    "source_level": "來源層級",
    "confidence": "信心度",
    "ai_data_center": "AI 資料中心",
    "ai_input_audit": "AI 入模審計",
    "report_confidence": "報告可信度",
    "ai_prompt_context": "AI 入模資料",
    "selected_source_count": "AI 入模來源數",
    "omitted_source_count": "未直接入模來源數",
    "official_sources": "官方來源數",
    "media_sources": "媒體來源數",
    "risk_or_counter_sources": "風險或反證來源數",
    "dated_sources": "有日期來源數",
    "prompt_context_chars": "入模資料字數",
    "available_sections": "已入模資料類型",
    "missing_sections": "缺少項目",
    "omitted_reason_counts": "未入模原因統計",
    "confidence_score": "可信度分數",
    "confidence_level": "可信度等級",
    "confidence_label": "可信度標籤",
    "passed": "檢查通過",
    "warnings": "提醒",
    "schema_errors": "格式檢查錯誤",
    "cross_segment_consistency": "跨段一致性",
    "segment_consistency": "跨段一致性"
  },
  "value_phrases": {
    "market_validated=false": "盤面尚未明確驗證",
    "market_validated=true": "盤面已有驗證",
    "news_stats.news_count_24h=0": "近 24 小時新聞熱度不足",
    "source_level=L1_official": "來源層級：官方來源",
    "source_level=L2_media": "來源層級：媒體來源",
    "source_level=L3": "來源層級：輔助來源",
    "confidence=medium": "信心度：中",
    "confidence=high": "信心度：高",
    "confidence=low": "信心度：低"
  }
}
